githubuser/__init__.py
githubuser/get_github_user.py
githubuser-1.0.1.dist-info/LICENSE.txt
githubuser-1.0.1.dist-info/METADATA
githubuser-1.0.1.dist-info/WHEEL
githubuser-1.0.1.dist-info/top_level.txt
githubuser-1.0.1.dist-info/RECORD
