Metadata-Version: 2.1
Name: githubuser
Version: 1.0.1
Summary: Find Github user basic details
Home-page: https://github.com/pranavvp10/githubuser
Author: Pranav V P
Author-email: <pranavvp07@gmail.com>
License: UNKNOWN
Keywords: python,Github,githubuser
Platform: UNKNOWN
Classifier: Development Status :: 3 - Alpha
Classifier: Intended Audience :: Education
Classifier: Programming Language :: Python :: 2
Classifier: Programming Language :: Python :: 3
Classifier: Operating System :: MacOS :: MacOS X
Classifier: License :: OSI Approved :: MIT License
Classifier: Operating System :: Microsoft :: Windows
Requires-Dist: requests
